README.rst
setup.py
mergic/__init__.py
mergic/mergic.py
mergic/test.py
mergic.egg-info/PKG-INFO
mergic.egg-info/SOURCES.txt
mergic.egg-info/dependency_links.txt
mergic.egg-info/entry_points.txt
mergic.egg-info/top_level.txt