Metadata-Version: 1.1
Name: mergic
Version: 0.0.7
Summary: workflow support for reproducible deduplication and merging
Home-page: https://github.com/ajschumacher/mergic
Author: Aaron Schumacher
Author-email: ajschumacher@gmail.com
License: MIT
Download-URL: https://github.com/ajschumacher/mergic/tarball/0.0.7
Platform: UNKNOWN
Classifier: Programming Language :: Python
Classifier: Programming Language :: Python :: 2.7
Classifier: License :: OSI Approved :: MIT License
Classifier: Development Status :: 2 - Pre-Alpha
